selkies_gstreamer/__init__.py
selkies_gstreamer/__main__.py
selkies_gstreamer/gamepad.py
selkies_gstreamer/gpu_monitor.py
selkies_gstreamer/gstwebrtc_app.py
selkies_gstreamer/input_event_codes.py
selkies_gstreamer/metrics.py
selkies_gstreamer/resize.py
selkies_gstreamer/signalling_web.py
selkies_gstreamer/system_monitor.py
selkies_gstreamer/watch_test.py
selkies_gstreamer/webrtc_input.py
selkies_gstreamer/webrtc_signalling.py
selkies_gstreamer-1.6.1.dist-info/METADATA
selkies_gstreamer-1.6.1.dist-info/WHEEL
selkies_gstreamer-1.6.1.dist-info/entry_points.txt
selkies_gstreamer-1.6.1.dist-info/top_level.txt
selkies_gstreamer-1.6.1.dist-info/RECORD
