Metadata-Version: 2.1
Name: selkies
Version: 1.6.1
Summary: Open-Source Low-Latency Linux WebRTC HTML5 Remote Desktop and 3D Graphics / Game Streaming Platform with GStreamer
Home-page: https://github.com/selkies-project/selkies
Author: "Dan Isla", "Seungmin Kim"
Author-email: "danisla@users.noreply.github.com", "8457324+ehfd@users.noreply.github.com"
Project-URL: Bug Tracker, https://github.com/selkies-project/selkies/issues
License: Mozilla Public License, version 2.0
Classifier: Programming Language :: Python :: 3
Requires-Python: >=3.8
Requires-Dist: websockets
Requires-Dist: basicauth
Requires-Dist: gputil
Requires-Dist: prometheus-client
Requires-Dist: msgpack
Requires-Dist: pynput
Requires-Dist: psutil
Requires-Dist: watchdog
Requires-Dist: Pillow
Requires-Dist: python-xlib
